configman/__init__.py
configman/commandline.py
configman/config_exceptions.py
configman/config_file_future_proxy.py
configman/config_manager.py
configman/converters.py
configman/datetime_util.py
configman/dotdict.py
configman/environment.py
configman/memoize.py
configman/namespace.py
configman/option.py
configman/orderedset.py
configman/required_config.py
configman/version.txt
configman/def_sources/__init__.py
configman/def_sources/for_argparse.py
configman/def_sources/for_json.py
configman/def_sources/for_mappings.py
configman/def_sources/for_modules.py
configman/tests/__init__.py
configman/tests/test_config_files.py
configman/tests/test_config_manager.py
configman/tests/test_converters.py
configman/tests/test_datetime_util.py
configman/tests/test_def_for_argparse.py
configman/tests/test_def_for_mappings.py
configman/tests/test_def_sources.py
configman/tests/test_dotdict.py
configman/tests/test_memoize.py
configman/tests/test_namespace.py
configman/tests/test_option.py
configman/tests/test_val_for_argparse.py
configman/tests/test_val_for_conf.py
configman/tests/test_val_for_configobj.py
configman/tests/test_val_for_getopt.py
configman/tests/test_val_for_json.py
configman/tests/test_val_for_mapping.py
configman/tests/test_val_for_modules.py
configman/tests/values_for_module_tests_1.py
configman/tests/values_for_module_tests_2.py
configman/tests/values_for_module_tests_3.py
configman/tests/values_for_module_tests_4.py
configman/value_sources/__init__.py
configman/value_sources/for_argparse.py
configman/value_sources/for_conf.py
configman/value_sources/for_configobj.py
configman/value_sources/for_getopt.py
configman/value_sources/for_json.py
configman/value_sources/for_mapping.py
configman/value_sources/for_modules.py
configman/value_sources/for_xml.py
configman/value_sources/source_exceptions.py
configman-1.3.0.dist-info/top_level.txt
configman-1.3.0.dist-info/METADATA
configman-1.3.0.dist-info/DESCRIPTION.rst
configman-1.3.0.dist-info/metadata.json
configman-1.3.0.dist-info/WHEEL
configman-1.3.0.dist-info/RECORD
