Metadata-Version: 2.0
Name: configman
Version: 1.3.0
Summary: Flexible reading and writing of namespaced configuration options
Home-page: https://github.com/mozilla/configman
Author: K Lars Lohn, Peter Bengtsson
Author-email: lars@mozilla.com, peterbe@mozilla.com
License: UNKNOWN
Platform: UNKNOWN
Classifier: Development Status :: 5 - Production/Stable
Classifier: License :: OSI Approved :: Mozilla Public License 2.0 (MPL 2.0)
Classifier: Programming Language :: Python
Classifier: Programming Language :: Python :: 2
Classifier: Programming Language :: Python :: 2.6
Classifier: Programming Language :: Python :: 2.7
Classifier: Programming Language :: Python :: 3
Classifier: Programming Language :: Python :: 3.3
Classifier: Programming Language :: Python :: 3.4
Classifier: Programming Language :: Python :: 3.5
Classifier: Intended Audience :: Developers
Classifier: Environment :: Console
Requires-Dist: configobj (>=4.7.2)
Requires-Dist: six
